hydroinform/DFS.py
hydroinform/Mike_river.py
hydroinform/NetCDF.py
hydroinform/__init__.py
hydroinform/core.py
hydroinform/dfs2gdal.py
hydroinform/hyimport2.py
hydroinform/hymod.py
hydroinform/hyplot.py
hydroinform/hyshape.py
hydroinform/ts_tools.py
hydroinform-0.1.17.dist-info/LICENSE
hydroinform-0.1.17.dist-info/METADATA
hydroinform-0.1.17.dist-info/WHEEL
hydroinform-0.1.17.dist-info/top_level.txt
hydroinform-0.1.17.dist-info/RECORD
