Metadata-Version: 2.1
Name: hydroinform
Version: 0.1.17
Summary: A steady-state stream model and python access to DFS-files
Home-page: http://hydroinform.dk
Author: Jan Gregersen and Jacob Gudbjerg
Author-email: jacobgudbjerg@gmail.com
Classifier: Programming Language :: Python
Classifier: License :: OSI Approved :: GNU General Public License (GPL)
Classifier: Operating System :: OS Independent
License-File: LICENSE
Requires-Dist: pyshp (>=2.1)
Requires-Dist: numpy
Requires-Dist: matplotlib
Requires-Dist: pythonnet
Requires-Dist: netCDF4
Requires-Dist: enum34 ; python_version < "3.4"
